FNC/FNC01.py
FNC/FNC02.py
FNC/FNC03.py
FNC/FNC04.py
FNC/FNC05.py
FNC/FNC06.py
FNC/FNC08.py
FNC/FNC09.py
FNC/FNC10.py
FNC/FNC11.py
FNC/FNC13.py
FNC/__init__.py
fnc_python-0.2.0.dist-info/LICENSE
fnc_python-0.2.0.dist-info/METADATA
fnc_python-0.2.0.dist-info/WHEEL
fnc_python-0.2.0.dist-info/top_level.txt
fnc_python-0.2.0.dist-info/RECORD
